safeguards/__init__.py
safeguards/llm.py
safeguards/metrics.py
safeguards/regex_model.py
safeguards/utils.py
safeguards/guardrails/__init__.py
safeguards/guardrails/base.py
safeguards/guardrails/manager.py
safeguards/guardrails/entity_recognition/ReadMe.md
safeguards/guardrails/entity_recognition/__init__.py
safeguards/guardrails/entity_recognition/llm_judge_entity_recognition_guardrail.py
safeguards/guardrails/entity_recognition/presidio_entity_recognition_guardrail.py
safeguards/guardrails/entity_recognition/regex_entity_recognition_guardrail.py
safeguards/guardrails/entity_recognition/transformers_entity_recognition_guardrail.py
safeguards/guardrails/entity_recognition/banned_terms_examples/banned_term_benchmark.py
safeguards/guardrails/entity_recognition/banned_terms_examples/banned_term_examples.py
safeguards/guardrails/entity_recognition/banned_terms_examples/run_llm_judge.py
safeguards/guardrails/entity_recognition/banned_terms_examples/run_regex_model.py
safeguards/guardrails/entity_recognition/pii_examples/pii_benchmark.py
safeguards/guardrails/entity_recognition/pii_examples/pii_benchmark_weave.py
safeguards/guardrails/entity_recognition/pii_examples/pii_test_examples.py
safeguards/guardrails/entity_recognition/pii_examples/run_presidio_model.py
safeguards/guardrails/entity_recognition/pii_examples/run_regex_model.py
safeguards/guardrails/entity_recognition/pii_examples/run_transformers.py
safeguards/guardrails/injection/__init__.py
safeguards/guardrails/injection/llm_guardrail.py
safeguards/guardrails/injection/prompts.py
safeguards/guardrails/injection/classifier_guardrail/__init__.py
safeguards/guardrails/injection/classifier_guardrail/classifier_guardrail.py
safeguards/guardrails/injection/classifier_guardrail/huggingface_classifier_guardrail.py
safeguards/guardrails/injection/classifier_guardrail/llama_prompt_guardrail.py
safeguards/guardrails/privilege_escalation/README.md
safeguards/guardrails/privilege_escalation/__init__.py
safeguards-0.0.6.dist-info/METADATA
safeguards-0.0.6.dist-info/WHEEL
safeguards-0.0.6.dist-info/top_level.txt
safeguards-0.0.6.dist-info/RECORD
