Metadata-Version: 2.2
Name: safeguards
Version: 0.0.6
Requires-Python: >=3.10
Requires-Dist: datasets>=3.1.0
Requires-Dist: detect-secrets>=1.5.0
Requires-Dist: evaluate>=0.4.3
Requires-Dist: google-generativeai>=0.8.3
Requires-Dist: hyperscan>=0.7.8
Requires-Dist: openai>=1.52.2
Requires-Dist: weave>=0.51.27
Requires-Dist: streamlit>=1.40.1
Requires-Dist: python-dotenv>=1.0.1
Requires-Dist: watchdog>=6.0.0
Requires-Dist: transformers>=4.46.3
Requires-Dist: instructor>=1.7.0
Requires-Dist: diskcache>=5.6.3
Requires-Dist: matplotlib>=3.9.3
Requires-Dist: plotly>=5.24.1
Requires-Dist: scikit-learn>=1.5.2
Requires-Dist: sqlparse>=0.5.2
Provides-Extra: presidio
Requires-Dist: presidio-analyzer>=2.2.355; extra == "presidio"
Requires-Dist: presidio-anonymizer>=2.2.355; extra == "presidio"
Provides-Extra: secrets
Requires-Dist: gibberish-detector>=0.1.1; extra == "secrets"
Requires-Dist: detect-secrets>=1.5.0; extra == "secrets"
Requires-Dist: hyperscan>=0.7.8; extra == "secrets"
Provides-Extra: dev
Requires-Dist: isort>=5.13.2; extra == "dev"
Requires-Dist: black>=24.10.0; extra == "dev"
Requires-Dist: ruff>=0.6.9; extra == "dev"
Requires-Dist: pip>=24.2; extra == "dev"
Requires-Dist: uv>=0.5.11; extra == "dev"
Requires-Dist: pytest>=8.3.4; extra == "dev"
Requires-Dist: hypothesis>=6.122.5; extra == "dev"
Provides-Extra: docs
Requires-Dist: mkdocs>=1.6.1; extra == "docs"
Requires-Dist: mkdocstrings>=0.26.1; extra == "docs"
Requires-Dist: mkdocstrings-python>=1.11.1; extra == "docs"
Requires-Dist: mkdocs-material>=9.5.39; extra == "docs"
Requires-Dist: mkdocs-minify-plugin>=0.8.0; extra == "docs"
Requires-Dist: mkdocs-glightbox>=0.4.0; extra == "docs"
Requires-Dist: mkdocs-jupyter>=0.25.0; extra == "docs"
Requires-Dist: jupyter>=1.1.1; extra == "docs"
Provides-Extra: test
Requires-Dist: pytest>=8.2.0; extra == "test"
Requires-Dist: pytest-asyncio>=0.23.6; extra == "test"
Requires-Dist: pytest-cov>=5.0.0; extra == "test"
Requires-Dist: pytest-xdist>=3.1.0; extra == "test"
Requires-Dist: hypothesis>=6.122.1; extra == "test"
